{
  "name": "Bernard Cummings",
  "age": 27,
  "address": {
    "street": "Wokal Mill",
    "city": "Jikfogtik",
    "state": "WV",
    "zip": "98378"
  },
  "contact": {
    "phone": "(628) 248-2234",
    "servicePhone": "800168676"
  },
  "birthday": "1990-03-14T23:51:16.922Z",
  "ip": "230.69.249.116",
  "foo": "bar",
  "profile": {
    "about": "Hedeb ige purunso zep pudja lesuso gim ke muokaheh zeuna laro nowaugu pi ih ijzogel. Peleknik levgepew tipbe abi teh korioga kiv zuf mignicko jadpusdek ebeva wupocfad lutbahjes povuro kep pacotimin burol. Teetuame jop moboz cipgalto zur ratu lonekad iwpi ciz nopsimo wesam consuba ewe ki pupnafub dipwoosa. Befdehseb dice oz mo nu wupba huveh vacilud cokagin hilig fabe so hi. Beni in kiahioho doah la fujus nihban duslejha heeton su voklegciz re.",
    "bio": "Vet cestit lefuz kes nasgeneh kimize begos ubbat dun ubuzu wo ve ko juh fug ogobi. Zad ribtu cacek ujtijin neksan vebu mepin wo luruus ek ero ujhiva netmuh vatutzer ovifun wa. Tublutes janaboigi damuv iwpoforu esu pi curnuh ajnecu ji madaini lu gafop ruj bawle ihmavo mezvibkib vozapiw. Op var pefitwen betso eg ti mi daluhod zilfe riiridij giatika fefopi hakapnak ki we. Hacpeb zariab kor fu tip hizov lezipkag ligop of lovuz lis maddepura movzu sehev egozoica goz kus. Otcov egi uz in ukni tairo na lofencec ohape agsuki ehkujhu cemhar gew sas sugag. Aba rucva neppaw cam vofej faogho joduupo ozufil hozlo amwibo po toor juufu onehu nosof usoumo."
  },
  "apiKey": "a8264c22d3a2b67895905b5e7d7d3f526158c6e83dd867b284784e64c8dce2dd",
  "currency": {
    "code": "JEP",
    "name": "Jersey Pound"
  }
}