{
  "name": "Derek Ortega",
  "age": 52,
  "address": {
    "street": "Gajo Lane",
    "city": "Aninara",
    "state": "NC",
    "zip": "70894"
  },
  "contact": {
    "phone": "(871) 682-1442",
    "servicePhone": "800843995"
  },
  "birthday": "1979-03-09T05:44:59.894Z",
  "ip": "192.61.109.91",
  "foo": "bar",
  "profile": {
    "about": "Paklu sioge ku owbitju fiwem vitogpiw jidbe la fukrasa kuj dopki pof mulcogumo ros guv atuome madibbi. En cu hoggog robjuzbit kucjol derwip kek jiruvusu vacvata pog modiz pikso gize funjeada fa jiz. Vodsavmo cep edrik ogo bukto nazuv nak aviusaz tocmiwi muhcoub tiw uzeha weramifet jekako. Rowvof zup oplurruh pokedcol con pe wuw evigohebo bup rivrib ofici nu rowcosjo. Mablo tu jovid pe pok helhuf mir ragzoil moip zazor vijfe va izomebur vi ubcoz. Giti kijopa jezcat wodo ni lehol vijne bi barvahvub guno suzzik pamoz fiov de ukivu sev uz.",
    "bio": "Fopwa migapna re kigis hehvi wakri towipi icoro cuwhu loaw joc ku. Ne bawi sez zongumo eno afohula fetnasa run laate te nooda balo kor. Ehaowi dupid uvi hevovaze zohpo bajmen pubane id inpewras wafic sibikzif sozfovi mu usjedo. Ekofemeki egijapmup op haz wusetci gib kon ramos kev ko ac nuevpur did hifevutep mi."
  },
  "apiKey": "07cea55c028c85683bee7c031fc7207c4013bf23183a42cdc05f6bd2320da0f0",
  "currency": {
    "code": "BZD",
    "name": "Belize Dollar"
  }
}